MANIFEST.in
README.md
setup.py
DataToolsJK.egg-info/PKG-INFO
DataToolsJK.egg-info/SOURCES.txt
DataToolsJK.egg-info/dependency_links.txt
DataToolsJK.egg-info/entry_points.txt
DataToolsJK.egg-info/not-zip-safe
DataToolsJK.egg-info/requires.txt
DataToolsJK.egg-info/top_level.txt
cli/__init__.py
cli/cli.py
cli/excel_tools.py
cli/common/__init__.py
cli/common/context_base.py
cli/common/decorator_base.py