Metadata-Version: 1.2
Name: DataToolsJK
Version: 1.0
Summary: 用例筛选工具
Home-page: https://github.com/Jakilo1996/CmdTools.git
Author: Jakiro
Author-email: 17709005281@163.com
License: UNKNOWN
Platform: UNKNOWN
Requires-Python: >=3.6
